chelexicon/__init__.py
chelexicon/tools/__init__.py
chelexicon/tools/sphinx_setup/__init__.py
chelexicon/tools/sphinx_setup/setup.py
chelexicon-1.0.0.dist-info/licenses/LICENSE
chelexicon-1.0.0.dist-info/METADATA
chelexicon-1.0.0.dist-info/WHEEL
chelexicon-1.0.0.dist-info/top_level.txt
chelexicon-1.0.0.dist-info/RECORD
