Metadata-Version: 2.4
Name: chelexicon
Version: 1.0.0
Summary: A wrapper for Sphinx that allows you to create an instance of SphinxSetup that will automatically configue Sphinx with minimal manual configuration.
Author: Chelsea Dax
License:                                  Apache License
Requires-Python: >=3.10
License-File: LICENSE
Dynamic: license-file
